<?xml version="1.0" encoding="UTF-8"?>
<results title="frequencies">
 <result title="frequency" word="MoO" count="332"/>
 <result title="frequency" word="/GO" count="114"/>
 <result title="frequency" word="micrometer" count="38"/>
 <result title="frequency" word="mAh" count="36"/>
 <result title="frequency" word="nanohoneycomb" count="35"/>
 <result title="frequency" word="capacity" count="33"/>
 <result title="frequency" word="Figure" count="31"/>
 <result title="frequency" word="layered" count="31"/>
 <result title="frequency" word="/GO‐," count="29"/>
 <result title="frequency" word="respectively." count="26"/>
 <result title="frequency" word="current" count="25"/>
 <result title="frequency" word="/GO‐" count="24"/>
 <result title="frequency" word=".%," count="22"/>
 <result title="frequency" word="/GO," count="22"/>
 <result title="frequency" word="attributed" count="22"/>
 <result title="frequency" word="prepared" count="21"/>
 <result title="frequency" word="{border-style" count="20"/>
 <result title="frequency" word="nanohoneycomb," count="19"/>
 <result title="frequency" word="px;}" count="18"/>
 <result title="frequency" word="structure" count="18"/>
 <result title="frequency" word="supports" count="18"/>
 <result title="frequency" word="#ffffff;}" count="17"/>
 <result title="frequency" word="analysis" count="17"/>
 <result title="frequency" word="density" count="17"/>
 <result title="frequency" word="particles" count="17"/>
 <result title="frequency" word="(NH" count="16"/>
 <result title="frequency" word="Wang" count="16"/>
 <result title="frequency" word="architectures" count="16"/>
 <result title="frequency" word="cycle" count="16"/>
 <result title="frequency" word="Mater." count="15"/>
 <result title="frequency" word="capacities" count="15"/>
 <result title="frequency" word="high" count="15"/>
 <result title="frequency" word="(Figure" count="14"/>
 <result title="frequency" word="higher" count="14"/>
 <result title="frequency" word="surface" count="14"/>
 <result title="frequency" word="Chem." count="13"/>
 <result title="frequency" word="Supporting" count="13"/>
 <result title="frequency" word="decomposition" count="13"/>
 <result title="frequency" word="performance" count="13"/>
 <result title="frequency" word="inside" count="12"/>
 <result title="frequency" word="ion" count="12"/>
 <result title="frequency" word="porous" count="12"/>
 <result title="frequency" word="pure" count="12"/>
 <result title="frequency" word="shows" count="12"/>
 <result title="frequency" word="using" count="12"/>
 <result title="frequency" word="weight" count="12"/>
 <result title="frequency" word="bulk" count="11"/>
 <result title="frequency" word="cycles," count="11"/>
 <result title="frequency" word="electrodes" count="11"/>
 <result title="frequency" word="exhibits" count="11"/>
 <result title="frequency" word="flexible" count="11"/>
 <result title="frequency" word="graphene" count="11"/>
 <result title="frequency" word="peaks" count="11"/>
 <result title="frequency" word="(typical)" count="10"/>
 <result title="frequency" word="ammonium" count="10"/>
 <result title="frequency" word="oxide" count="10"/>
 <result title="frequency" word="particulates" count="10"/>
 <result title="frequency" word="provided" count="10"/>
 <result title="frequency" word="rate" count="10"/>
 <result title="frequency" word="structures" count="10"/>
 <result title="frequency" word="tested" count="10"/>
 <result title="frequency" word="used" count="10"/>
 <result title="frequency" word=".–." count="9"/>
 <result title="frequency" word="Science" count="9"/>
 <result title="frequency" word="Zhang" count="9"/>
 <result title="frequency" word="discharge" count="9"/>
 <result title="frequency" word="employed" count="9"/>
 <result title="frequency" word="peak" count="9"/>
 <result title="frequency" word="possibly" count="9"/>
 <result title="frequency" word="ratios" count="9"/>
 <result title="frequency" word="reference" count="9"/>
 <result title="frequency" word="size" count="9"/>
 <result title="frequency" word=".°," count="8"/>
 <result title="frequency" word="Chen" count="8"/>
 <result title="frequency" word="FIB" count="8"/>
 <result title="frequency" word="achieved" count="8"/>
 <result title="frequency" word="corresponding" count="8"/>
 <result title="frequency" word="cycle," count="8"/>
 <result title="frequency" word="electron" count="8"/>
 <result title="frequency" word="initial" count="8"/>
 <result title="frequency" word="materials" count="8"/>
 <result title="frequency" word="nanoscale" count="8"/>
 <result title="frequency" word="patterns" count="8"/>
 <result title="frequency" word="px;" count="8"/>
 <result title="frequency" word="ratio" count="8"/>
 <result title="frequency" word="theoretical" count="8"/>
 <result title="frequency" word="water" count="8"/>
 <result title="frequency" word="{font-family" count="8"/>
 <result title="frequency" word="ACS" count="7"/>
 <result title="frequency" word="CEs" count="7"/>
 <result title="frequency" word="GO." count="7"/>
 <result title="frequency" word="However," count="7"/>
 <result title="frequency" word="Information)." count="7"/>
 <result title="frequency" word="Nano" count="7"/>
 <result title="frequency" word="SEM" count="7"/>
 <result title="frequency" word="Shaanxi" count="7"/>
 <result title="frequency" word="Sun" count="7"/>
 <result title="frequency" word="Technology" count="7"/>
 <result title="frequency" word="XRD" count="7"/>
 <result title="frequency" word="Yang" count="7"/>
 <result title="frequency" word="curves" count="7"/>
 <result title="frequency" word="electrochemical" count="7"/>
 <result title="frequency" word="font-size" count="7"/>
 <result title="frequency" word="lithium" count="7"/>
 <result title="frequency" word="performed" count="7"/>
 <result title="frequency" word="strongly" count="7"/>
 <result title="frequency" word="supported" count="7"/>
 <result title="frequency" word="(MoO" count="6"/>
 <result title="frequency" word="Guo" count="6"/>
 <result title="frequency" word="Huang" count="6"/>
 <result title="frequency" word="TEM" count="6"/>
 <result title="frequency" word="TGA" count="6"/>
 <result title="frequency" word="University" count="6"/>
 <result title="frequency" word="architectures," count="6"/>
 <result title="frequency" word="average" count="6"/>
 <result title="frequency" word="cycles" count="6"/>
 <result title="frequency" word="discharge/charge" count="6"/>
 <result title="frequency" word="displays" count="6"/>
 <result title="frequency" word="double;" count="6"/>
 <result title="frequency" word="mixture" count="6"/>
 <result title="frequency" word="molybdate/GO" count="6"/>
 <result title="frequency" word="particles," count="6"/>
 <result title="frequency" word="shown" count="6"/>
 <result title="frequency" word="spectroscopy" count="6"/>
 <result title="frequency" word="synthesized" count="6"/>
 <result title="frequency" word="ultrafine" count="6"/>
 <result title="frequency" word="value" count="6"/>
 <result title="frequency" word="(C)" count="5"/>
 <result title="frequency" word="/GO‐." count="5"/>
 <result title="frequency" word="China" count="5"/>
 <result title="frequency" word="Energy" count="5"/>
 <result title="frequency" word="Information." count="5"/>
 <result title="frequency" word="Liu" count="5"/>
 <result title="frequency" word="No." count="5"/>
 <result title="frequency" word="Table" count="5"/>
 <result title="frequency" word="X‐ray" count="5"/>
 <result title="frequency" word="active" count="5"/>
 <result title="frequency" word="air" count="5"/>
 <result title="frequency" word="anode" count="5"/>
 <result title="frequency" word="area" count="5"/>
 <result title="frequency" word="border-color" count="5"/>
 <result title="frequency" word="border-width" count="5"/>
 <result title="frequency" word="connected" count="5"/>
 <result title="frequency" word="consistent" count="5"/>
 <result title="frequency" word="cycled" count="5"/>
 <result title="frequency" word="deliver" count="5"/>
 <result title="frequency" word="dried" count="5"/>
 <result title="frequency" word="form" count="5"/>
 <result title="frequency" word="heating" count="5"/>
 <result title="frequency" word="honeycomb‐like" count="5"/>
 <result title="frequency" word="increase" count="5"/>
 <result title="frequency" word="increases" count="5"/>
 <result title="frequency" word="large" count="5"/>
 <result title="frequency" word="loss" count="5"/>
 <result title="frequency" word="materials." count="5"/>
 <result title="frequency" word="metal" count="5"/>
 <result title="frequency" word="microscopy" count="5"/>
 <result title="frequency" word="obtained" count="5"/>
 <result title="frequency" word="particle" count="5"/>
 <result title="frequency" word="preform" count="5"/>
 <result title="frequency" word="process" count="5"/>
 <result title="frequency" word="resistance" count="5"/>
 <result title="frequency" word="reversible" count="5"/>
 <result title="frequency" word="samples" count="5"/>
 <result title="frequency" word="scanning" count="5"/>
 <result title="frequency" word="similar" count="5"/>
 <result title="frequency" word="solid;" count="5"/>
 <result title="frequency" word="storage" count="5"/>
 <result title="frequency" word="transfer" count="5"/>
 <result title="frequency" word="vacuum" count="5"/>
 <result title="frequency" word="voltage" count="5"/>
 <result title="frequency" word="{font-style" count="5"/>
 <result title="frequency" word="{font-weight" count="5"/>
 <result title="frequency" word="()," count="4"/>
 <result title="frequency" word=".%." count="4"/>
 <result title="frequency" word="Academic" count="4"/>
 <result title="frequency" word="Adv." count="4"/>
 <result title="frequency" word="Cao" count="4"/>
 <result title="frequency" word="FIB–SEM" count="4"/>
 <result title="frequency" word="Foundation" count="4"/>
 <result title="frequency" word="Key" count="4"/>
 <result title="frequency" word="Kim" count="4"/>
 <result title="frequency" word="Mo," count="4"/>
 <result title="frequency" word="Shi" count="4"/>
 <result title="frequency" word="Soc." count="4"/>
 <result title="frequency" word="added" count="4"/>
 <result title="frequency" word="analysis." count="4"/>
 <result title="frequency" word="assigned" count="4"/>
 <result title="frequency" word="atmosphere" count="4"/>
 <result title="frequency" word="bold" count="4"/>
 <result title="frequency" word="carbon" count="4"/>
 <result title="frequency" word="charge" count="4"/>
 <result title="frequency" word="composed" count="4"/>
 <result title="frequency" word="constructed" count="4"/>
 <result title="frequency" word="conversion" count="4"/>
 <result title="frequency" word="courier;" count="4"/>
 <result title="frequency" word="differential" count="4"/>
 <result title="frequency" word="display" count="4"/>
 <result title="frequency" word="em;" count="4"/>
 <result title="frequency" word="fixed" count="4"/>
 <result title="frequency" word="image" count="4"/>
 <result title="frequency" word="images" count="4"/>
 <result title="frequency" word="impedance" count="4"/>
 <result title="frequency" word="low" count="4"/>
 <result title="frequency" word="material" count="4"/>
 <result title="frequency" word="microscope" count="4"/>
 <result title="frequency" word="min" count="4"/>
 <result title="frequency" word="nanoarchitectures" count="4"/>
 <result title="frequency" word="order" count="4"/>
 <result title="frequency" word="percentage" count="4"/>
 <result title="frequency" word="preform‐" count="4"/>
 <result title="frequency" word="preform‐," count="4"/>
 <result title="frequency" word="pt;}" count="4"/>
 <result title="frequency" word="quantity" count="4"/>
 <result title="frequency" word="quartz" count="4"/>
 <result title="frequency" word="significant" count="4"/>
 <result title="frequency" word="skeleton" count="4"/>
 <result title="frequency" word="starting" count="4"/>
 <result title="frequency" word="them," count="4"/>
 <result title="frequency" word="times" count="4"/>
 <result title="frequency" word="washed" count="4"/>
 <result title="frequency" word="°C," count="4"/>
</results>
