<?xml version="1.0" encoding="UTF-8"?>
<results title="frequencies">
 <result title="frequency" word="α-Fe" count="143"/>
 <result title="frequency" word="capacity" count="23"/>
 <result title="frequency" word="Chem" count="22"/>
 <result title="frequency" word="concentration" count="21"/>
 <result title="frequency" word=",-diaminopropane" count="20"/>
 <result title="frequency" word="aspect" count="20"/>
 <result title="frequency" word="ratio" count="20"/>
 <result title="frequency" word="{border-style" count="20"/>
 <result title="frequency" word="mAh" count="19"/>
 <result title="frequency" word="Wang" count="18"/>
 <result title="frequency" word="px;}" count="18"/>
 <result title="frequency" word="synthesis" count="18"/>
 <result title="frequency" word="#ffffff;}" count="17"/>
 <result title="frequency" word="-D." count="17"/>
 <result title="frequency" word="diamine" count="17"/>
 <result title="frequency" word="obtained" count="17"/>
 <result title="frequency" word="reaction" count="17"/>
 <result title="frequency" word="Fig." count="16"/>
 <result title="frequency" word="Mater" count="16"/>
 <result title="frequency" word="nanorod" count="16"/>
 <result title="frequency" word="nanorods" count="16"/>
 <result title="frequency" word="SCA" count="15"/>
 <result title="frequency" word="formation" count="15"/>
 <result title="frequency" word="samples" count="15"/>
 <result title="frequency" word="length" count="14"/>
 <result title="frequency" word="nanoparticles" count="14"/>
 <result title="frequency" word="-D.," count="13"/>
 <result title="frequency" word="-E." count="13"/>
 <result title="frequency" word="crystal" count="13"/>
 <result title="frequency" word="cycle" count="13"/>
 <result title="frequency" word="electrochemical" count="13"/>
 <result title="frequency" word="growth" count="13"/>
 <result title="frequency" word="lithium" count="13"/>
 <result title="frequency" word="performance" count="13"/>
 <result title="frequency" word="range" count="13"/>
 <result title="frequency" word="-E.," count="12"/>
 <result title="frequency" word="ethylenediamine" count="12"/>
 <result title="frequency" word="ferric" count="12"/>
 <result title="frequency" word="morphology" count="12"/>
 <result title="frequency" word="Zhang" count="11"/>
 <result title="frequency" word="carbon" count="11"/>
 <result title="frequency" word="interaction" count="11"/>
 <result title="frequency" word="phase" count="11"/>
 <result title="frequency" word="(discharge)" count="10"/>
 <result title="frequency" word="Liu" count="10"/>
 <result title="frequency" word="ability" count="10"/>
 <result title="frequency" word="applied" count="10"/>
 <result title="frequency" word="density" count="10"/>
 <result title="frequency" word="rate" count="10"/>
 <result title="frequency" word="shape-controlling" count="10"/>
 <result title="frequency" word="spherical" count="10"/>
 <result title="frequency" word="steric" count="10"/>
 <result title="frequency" word="higher" count="9"/>
 <result title="frequency" word="particle" count="9"/>
 <result title="frequency" word="particles" count="9"/>
 <result title="frequency" word="rod" count="9"/>
 <result title="frequency" word="voltage" count="9"/>
 <result title="frequency" word=",-diaminobutane" count="8"/>
 <result title="frequency" word=",-diaminopropane," count="8"/>
 <result title="frequency" word="-B." count="8"/>
 <result title="frequency" word="./DAP" count="8"/>
 <result title="frequency" word="./EDA" count="8"/>
 <result title="frequency" word="Figure" count="8"/>
 <result title="frequency" word="complex" count="8"/>
 <result title="frequency" word="cycling" count="8"/>
 <result title="frequency" word="delithiation" count="8"/>
 <result title="frequency" word="diamines" count="8"/>
 <result title="frequency" word="electron" count="8"/>
 <result title="frequency" word="ethylenediamine," count="8"/>
 <result title="frequency" word="hydrothermal" count="8"/>
 <result title="frequency" word="ions" count="8"/>
 <result title="frequency" word="px;" count="8"/>
 <result title="frequency" word="terms" count="8"/>
 <result title="frequency" word="test" count="8"/>
 <result title="frequency" word="{font-family" count="8"/>
 <result title="frequency" word="(α-Fe" count="7"/>
 <result title="frequency" word=",-diaminobutane," count="7"/>
 <result title="frequency" word="N-methylethylenediamine" count="7"/>
 <result title="frequency" word="Phys" count="7"/>
 <result title="frequency" word="Sci" count="7"/>
 <result title="frequency" word="conversion" count="7"/>
 <result title="frequency" word="current" count="7"/>
 <result title="frequency" word="derivatives" count="7"/>
 <result title="frequency" word="diameter:" count="7"/>
 <result title="frequency" word="electrode" count="7"/>
 <result title="frequency" word="elongated" count="7"/>
 <result title="frequency" word="font-size" count="7"/>
 <result title="frequency" word="groups" count="7"/>
 <result title="frequency" word="high" count="7"/>
 <result title="frequency" word="increased" count="7"/>
 <result title="frequency" word="iron" count="7"/>
 <result title="frequency" word="leading" count="7"/>
 <result title="frequency" word="lithiation" count="7"/>
 <result title="frequency" word="lithium-ion" count="7"/>
 <result title="frequency" word="materials" count="7"/>
 <result title="frequency" word="products" count="7"/>
 <result title="frequency" word="resulting" count="7"/>
 <result title="frequency" word="species" count="7"/>
 <result title="frequency" word="using" count="7"/>
 <result title="frequency" word="(mAh" count="6"/>
 <result title="frequency" word="FeOOH" count="6"/>
 <result title="frequency" word="SCAs" count="6"/>
 <result title="frequency" word="Table" count="6"/>
 <result title="frequency" word="charge" count="6"/>
 <result title="frequency" word="cycles" count="6"/>
 <result title="frequency" word="different" count="6"/>
 <result title="frequency" word="direction" count="6"/>
 <result title="frequency" word="double;" count="6"/>
 <result title="frequency" word="indicating" count="6"/>
 <result title="frequency" word="lengths" count="6"/>
 <result title="frequency" word="located" count="6"/>
 <result title="frequency" word="nanometer-scale" count="6"/>
 <result title="frequency" word="ratios" count="6"/>
 <result title="frequency" word="reported" count="6"/>
 <result title="frequency" word="shape" count="6"/>
 <result title="frequency" word="surface" count="6"/>
 <result title="frequency" word="used" count="6"/>
 <result title="frequency" word="values" count="6"/>
 <result title="frequency" word="various" count="6"/>
 <result title="frequency" word="vicinal" count="6"/>
 <result title="frequency" word="(%," count="5"/>
 <result title="frequency" word="Beilstein" count="5"/>
 <result title="frequency" word="Chen" count="5"/>
 <result title="frequency" word="FESEM" count="5"/>
 <result title="frequency" word="Lett" count="5"/>
 <result title="frequency" word="Soc" count="5"/>
 <result title="frequency" word="Sun" count="5"/>
 <result title="frequency" word="Tarascon" count="5"/>
 <result title="frequency" word="Varied" count="5"/>
 <result title="frequency" word="[]," count="5"/>
 <result title="frequency" word="approaches" count="5"/>
 <result title="frequency" word="average" count="5"/>
 <result title="frequency" word="battery" count="5"/>
 <result title="frequency" word="border-color" count="5"/>
 <result title="frequency" word="border-width" count="5"/>
 <result title="frequency" word="capacities" count="5"/>
 <result title="frequency" word="complexes" count="5"/>
 <result title="frequency" word="constant" count="5"/>
 <result title="frequency" word="content:" count="5"/>
 <result title="frequency" word="diameter" count="5"/>
 <result title="frequency" word="fixed" count="5"/>
 <result title="frequency" word="impact" count="5"/>
 <result title="frequency" word="including" count="5"/>
 <result title="frequency" word="lattice" count="5"/>
 <result title="frequency" word="length:" count="5"/>
 <result title="frequency" word="longer" count="5"/>
 <result title="frequency" word="series" count="5"/>
 <result title="frequency" word="solid;" count="5"/>
 <result title="frequency" word="synthesized" count="5"/>
 <result title="frequency" word="transformation" count="5"/>
 <result title="frequency" word="varied" count="5"/>
 <result title="frequency" word="volume" count="5"/>
 <result title="frequency" word="{font-style" count="5"/>
 <result title="frequency" word="{font-weight" count="5"/>
 <result title="frequency" word="Adv" count="4"/>
 <result title="frequency" word="Angew" count="4"/>
 <result title="frequency" word="C-group" count="4"/>
 <result title="frequency" word="Electrochem" count="4"/>
 <result title="frequency" word="Guo" count="4"/>
 <result title="frequency" word="J-M" count="4"/>
 <result title="frequency" word="LIBs" count="4"/>
 <result title="frequency" word="Madhavi" count="4"/>
 <result title="frequency" word="N-methylethylenediamine," count="4"/>
 <result title="frequency" word="Nanotechnology" count="4"/>
 <result title="frequency" word="SCA." count="4"/>
 <result title="frequency" word="Shen" count="4"/>
 <result title="frequency" word="XRD" count="4"/>
 <result title="frequency" word="additional" count="4"/>
 <result title="frequency" word="agreement" count="4"/>
 <result title="frequency" word="amine" count="4"/>
 <result title="frequency" word="attributed" count="4"/>
 <result title="frequency" word="bold" count="4"/>
 <result title="frequency" word="calculated" count="4"/>
 <result title="frequency" word="concentrations" count="4"/>
 <result title="frequency" word="conditions" count="4"/>
 <result title="frequency" word="control" count="4"/>
 <result title="frequency" word="coordinated" count="4"/>
 <result title="frequency" word="courier;" count="4"/>
 <result title="frequency" word="crystallized" count="4"/>
 <result title="frequency" word="delithiation/lithiation" count="4"/>
 <result title="frequency" word="direct" count="4"/>
 <result title="frequency" word="effect" count="4"/>
 <result title="frequency" word="effect)" count="4"/>
 <result title="frequency" word="em;" count="4"/>
 <result title="frequency" word="facets" count="4"/>
 <result title="frequency" word="following" count="4"/>
 <result title="frequency" word="general," count="4"/>
 <result title="frequency" word="graphite" count="4"/>
 <result title="frequency" word="hindrance." count="4"/>
 <result title="frequency" word="hydroxyl" count="4"/>
 <result title="frequency" word="images" count="4"/>
 <result title="frequency" word="improved" count="4"/>
 <result title="frequency" word="increase" count="4"/>
 <result title="frequency" word="kept" count="4"/>
 <result title="frequency" word="leads" count="4"/>
 <result title="frequency" word="loss" count="4"/>
 <result title="frequency" word="low" count="4"/>
 <result title="frequency" word="mechanism" count="4"/>
 <result title="frequency" word="metal" count="4"/>
 <result title="frequency" word="micrometer-sized" count="4"/>
 <result title="frequency" word="oxide" count="4"/>
 <result title="frequency" word="position" count="4"/>
 <result title="frequency" word="presented" count="4"/>
 <result title="frequency" word="process" count="4"/>
 <result title="frequency" word="pt;}" count="4"/>
 <result title="frequency" word="results" count="4"/>
 <result title="frequency" word="sample" count="4"/>
 <result title="frequency" word="second" count="4"/>
 <result title="frequency" word="set" count="4"/>
 <result title="frequency" word="showed" count="4"/>
 <result title="frequency" word="shows" count="4"/>
 <result title="frequency" word="solution" count="4"/>
 <result title="frequency" word="specified" count="4"/>
 <result title="frequency" word="superior" count="4"/>
 <result title="frequency" word="supports" count="4"/>
 <result title="frequency" word="value" count="4"/>
 <result title="frequency" word="voltammetry" count="4"/>
 <result title="frequency" word="≈.." count="4"/>
</results>
